[{"args":{"name":"swapper"},"cat":"__metadata","name":"thread_name","ph":"M","pid":0,"tid":0,"ts":0},
{"args":{"name":"CrBrowserMain"},"cat":"__metadata","name":"thread_name","ph":"M","pid":27916,"tid":27256,"ts":0},
{"args":{"name":"Compositor"},"cat":"__metadata","name":"thread_name","ph":"M","pid":55496,"tid":38460,"ts":0},
{"args":{"name":"CrRendererMain"},"cat":"__metadata","name":"thread_name","ph":"M","pid":55496,"tid":22724,"ts":0},
{"args":{"name":"Chrome_IOThread"},"cat":"__metadata","name":"thread_name","ph":"M","pid":27916,"tid":55712,"ts":0},
{"args":{"name":"VizCompositorThread"},"cat":"__metadata","name":"thread_name","ph":"M","pid":39252,"tid":21436,"ts":0},
{"args":{"name":"CrGpuMain"},"cat":"__metadata","name":"thread_name","ph":"M","pid":39252,"tid":22868,"ts":0},
{"args":{"name":"GpuVSyncThread"},"cat":"__metadata","name":"thread_name","ph":"M","pid":39252,"tid":37808,"ts":0},
{"args":{"name":"Chrome_ChildIOThread"},"cat":"__metadata","name":"thread_name","ph":"M","pid":55496,"tid":38520,"ts":0},
{"args":{"name":"ThreadPoolForegroundWorker"},"cat":"__metadata","name":"thread_name","ph":"M","pid":55496,"tid":19640,"ts":0},
{"args":{"name":"ThreadPoolForegroundWorker"},"cat":"__metadata","name":"thread_name","ph":"M","pid":55496,"tid":35740,"ts":0},
{"args":{"name":"CompositorTileWorker1"},"cat":"__metadata","name":"thread_name","ph":"M","pid":55496,"tid":47816,"ts":0},
{"args":{"name":"ThreadPoolServiceThread"},"cat":"__metadata","name":"thread_name","ph":"M","pid":27916,"tid":39396,"ts":0},
{"args":{"name":"CompositorTileWorker3"},"cat":"__metadata","name":"thread_name","ph":"M","pid":55496,"tid":14732,"ts":0},
{"args":{"name":"CompositorTileWorker4"},"cat":"__metadata","name":"thread_name","ph":"M","pid":55496,"tid":45912,"ts":0},
{"args":{"name":"CompositorTileWorker2"},"cat":"__metadata","name":"thread_name","ph":"M","pid":55496,"tid":31812,"ts":0},
{"args":{"name":"ThreadPoolServiceThread"},"cat":"__metadata","name":"thread_name","ph":"M","pid":39252,"tid":21500,"ts":0},
{"args":{"name":"ThreadPoolServiceThread"},"cat":"__metadata","name":"thread_name","ph":"M","pid":55496,"tid":38664,"ts":0},
{"args":{"name":"CompositorTileWorker1"},"cat":"__metadata","name":"thread_name","ph":"M","pid":27916,"tid":6488,"ts":0},
{"args":{"name":"ThreadPoolForegroundWorker"},"cat":"__metadata","name":"thread_name","ph":"M","pid":55496,"tid":18016,"ts":0},
{"args":{"name":"ThreadPoolForegroundWorker"},"cat":"__metadata","name":"thread_name","ph":"M","pid":55496,"tid":52360,"ts":0},
{"args":{"name":"ThreadPoolForegroundWorker"},"cat":"__metadata","name":"thread_name","ph":"M","pid":55496,"tid":2992,"ts":0},
{"args":{"name":"ThreadPoolForegroundWorker"},"cat":"__metadata","name":"thread_name","ph":"M","pid":55496,"tid":40388,"ts":0},
{"args":{"name":"ThreadPoolForegroundWorker"},"cat":"__metadata","name":"thread_name","ph":"M","pid":55496,"tid":35708,"ts":0},
